{
	"m_AtlasName": "",
	"m_Border": {
		"m_W": 0,
		"m_X": 0,
		"m_Y": 0,
		"m_Z": 0
	},
	"m_CorrespondingSourceObject": { "m_Collection": "resources.assets", "m_PathID": 0 },
	"m_Extrude": 1,
	"m_HideFlags": 0,
	"m_IsPolygon": false,
	"m_Name": "ITM_GreenColouredPen_001",
	"m_Offset": {
		"m_X": 2.0000007,
		"m_Y": 0.024686243
	},
	"m_PackingTag": "",
	"m_Pivot": {
		"m_X": 0.5417132,
		"m_Y": 0.5005154
	},
	"m_PixelsToUnits": 50,
	"m_PrefabInternal": { "m_Collection": "resources.assets", "m_PathID": 0 },
	"m_RD": {
		"m_AlphaTexture": { "m_Collection": "resources.assets", "m_PathID": 0 },
		"m_Indices": [
			9,
			8,
			6,
			7,
			6,
			8,
			3,
			6,
			7,
			5,
			6,
			3,
			4,
			5,
			3,
			1,
			4,
			3,
			0,
			1,
			3,
			2,
			1,
			0
		],
		"m_SettingsRaw": 67,
		"m_Texture": { "m_Collection": "resources.assets", "m_PathID": 861 },
		"m_TextureRect": {
			"m_Height": 47.897125,
			"m_Width": 47.946495,
			"m_X": 1526.0267,
			"m_Y": 116.02675
		},
		"m_TextureRectOffset": {
			"m_X": 0,
			"m_Y": 0
		},
		"m_UvTransform": {
			"m_W": 140,
			"m_X": 50,
			"m_Y": 1552,
			"m_Z": 50
		},
		"m_Vertices": [
			{
				"m_Pos": {
					"m_X": 0.32,
					"m_Y": 0.48,
					"m_Z": 0
				}
			},
			{
				"m_Pos": {
					"m_X": 0.44,
					"m_Y": 0.1,
					"m_Z": 0
				}
			},
			{
				"m_Pos": {
					"m_X": 0.44,
					"m_Y": 0.42,
					"m_Z": 0
				}
			},
			{
				"m_Pos": {
					"m_X": 0.14,
					"m_Y": 0.48,
					"m_Z": 0
				}
			},
			{
				"m_Pos": {
					"m_X": -0.2,
					"m_Y": -0.38,
					"m_Z": 0
				}
			},
			{
				"m_Pos": {
					"m_X": -0.34,
					"m_Y": -0.48,
					"m_Z": 0
				}
			},
			{
				"m_Pos": {
					"m_X": -0.46,
					"m_Y": -0.48,
					"m_Z": 0
				}
			},
			{
				"m_Pos": {
					"m_X": -0.5,
					"m_Y": -0.24,
					"m_Z": 0
				}
			},
			{
				"m_Pos": {
					"m_X": -0.52,
					"m_Y": -0.3,
					"m_Z": 0
				}
			},
			{
				"m_Pos": {
					"m_X": -0.52,
					"m_Y": -0.46,
					"m_Z": 0
				}
			}
		]
	},
	"m_Rect": {
		"m_Height": 47.897125,
		"m_Width": 47.946495,
		"m_X": 1526.0267,
		"m_Y": 116.02675
	}
}